src/__init__.py
src/calculator.py
calc_project_christian-0.0.1.dist-info/METADATA
calc_project_christian-0.0.1.dist-info/WHEEL
calc_project_christian-0.0.1.dist-info/licenses/licence.txt
calc_project_christian-0.0.1.dist-info/RECORD
