Metadata-Version: 2.1
Name: calc_project_christian
Version: 0.0.1
Summary: A small calculator that can do various calculations. Read the README file
Author-email: Christian Agerup <cagerup@gmail.com>
License-File: licence.txt
Classifier: License :: OSI Approved :: MIT License
Classifier: Operating System :: OS Independent
Classifier: Programming Language :: Python :: 3
Requires-Python: >=3.7
